MANIFEST.in
setup.cfg
setup.py
nfq/__init__.py
nfq/conductor/__init__.py
nfq/conductor/config.py
nfq/conductor/daemon.py
nfq/conductor/db.py
nfq/conductor/runner.py
nfq/conductor/server.py
nfq/conductor/submit.py
nfq/conductor/web.py
nfq/conductor/ws.py
nfq/conductor/templates/base.html
nfq/conductor/templates/config.html
nfq/conductor/templates/daemon.html
nfq/conductor/templates/daemons.html
nfq/conductor/templates/index.html
nfq/conductor/templates/list.html
nfq/conductor/templates/posted.html
nfq_conductor.egg-info/PKG-INFO
nfq_conductor.egg-info/SOURCES.txt
nfq_conductor.egg-info/dependency_links.txt
nfq_conductor.egg-info/entry_points.txt
nfq_conductor.egg-info/not-zip-safe
nfq_conductor.egg-info/requires.txt
nfq_conductor.egg-info/top_level.txt