Metadata-Version: 1.0
Name: nfq-conductor
Version: 0.3
Summary: NFQ Solutions tool for orchestration
Home-page: UNKNOWN
Author: NFQ Solutions
Author-email: solutions@nfq.es
License: UNKNOWN
Platform: UNKNOWN
